CHANGES.rst
CONTRIBUTORS.rst
MANIFEST.in
README.rst
requirements.txt
setup.cfg
setup.py
docs/LICENSE.GPL
docs/LICENSE.rst
docs/index.rst
src/collective/__init__.py
src/collective.tiles.collection.egg-info/PKG-INFO
src/collective.tiles.collection.egg-info/SOURCES.txt
src/collective.tiles.collection.egg-info/dependency_links.txt
src/collective.tiles.collection.egg-info/entry_points.txt
src/collective.tiles.collection.egg-info/namespace_packages.txt
src/collective.tiles.collection.egg-info/not-zip-safe
src/collective.tiles.collection.egg-info/requires.txt
src/collective.tiles.collection.egg-info/top_level.txt
src/collective/tiles/__init__.py
src/collective/tiles/collection/__init__.py
src/collective/tiles/collection/collection.py
src/collective/tiles/collection/configure.zcml
src/collective/tiles/collection/interfaces.py
src/collective/tiles/collection/setuphandlers.py
src/collective/tiles/collection/testing.py
src/collective/tiles/collection/vocabularies.py
src/collective/tiles/collection/browser/__init__.py
src/collective/tiles/collection/browser/base_view.py
src/collective/tiles/collection/browser/configure.zcml
src/collective/tiles/collection/browser/overrides/.gitkeep
src/collective/tiles/collection/browser/static/.gitkeep
src/collective/tiles/collection/browser/templates/base_view.pt
src/collective/tiles/collection/browser/templates/collection_tile.pt
src/collective/tiles/collection/locales/collective.tiles.collection.pot
src/collective/tiles/collection/locales/update.sh
src/collective/tiles/collection/locales/it/LC_MESSAGES/collective.tiles.collection.po
src/collective/tiles/collection/mosaicsupport/__init__.py
src/collective/tiles/collection/mosaicsupport/configure.zcml
src/collective/tiles/collection/mosaicsupport/profiles/default/metadata.xml
src/collective/tiles/collection/mosaicsupport/profiles/default/registry.xml
src/collective/tiles/collection/profiles/default/browserlayer.xml
src/collective/tiles/collection/profiles/default/metadata.xml
src/collective/tiles/collection/profiles/default/registry.xml
src/collective/tiles/collection/profiles/uninstall/browserlayer.xml
src/collective/tiles/collection/profiles/uninstall/registry.xml
src/collective/tiles/collection/tests/__init__.py
src/collective/tiles/collection/tests/test_robot.py
src/collective/tiles/collection/tests/test_setup.py
src/collective/tiles/collection/tests/robot/test_example.robot